py_imports/__init__.py
py_imports/ast_analyzers.py
py_imports/base/__init__.py
py_imports/base/models.py
py_imports/exceptions.py
py_imports/manager.py
py_imports/mixins.py
py_imports-1.3.0.dist-info/WHEEL
py_imports-1.3.0.dist-info/METADATA
py_imports-1.3.0.dist-info/RECORD
