Metadata-Version: 2.1
Name: py-imports
Version: 1.3.0
Summary: Python Toolkit to imports introspection
Home-page: https://github.com/AndresBena19/py-imports.git
Author: Andres
Author-email: andresbenavides404@gmail.com
Requires-Python: >=3.7,<4.0
Classifier: Intended Audience :: Developers
Classifier: License :: OSI Approved :: MIT License
Classifier: Operating System :: MacOS :: MacOS X
Classifier: Operating System :: Microsoft :: Windows
Classifier: Operating System :: POSIX
Classifier: Programming Language :: Python
Classifier: Programming Language :: Python :: 3
Classifier: Programming Language :: Python :: 3.10
Classifier: Programming Language :: Python :: 3.7
Classifier: Programming Language :: Python :: 3.8
Classifier: Programming Language :: Python :: 3.9
Classifier: Topic :: Software Development
Classifier: Topic :: Software Development :: Libraries
Classifier: Topic :: Utilities
Requires-Dist: pyflakes (==2.4.0)
Project-URL: Repository, https://github.com/AndresBena19/py-imports.git
